[
    {
        "frame": 29,
        "event": "mousedown",
        "description": "A mousedown event is initiated on an empty area of the Windows XP desktop background. \n"
    },
    {
        "frame": 50,
        "event": "mousedown",
        "description": "The user right-clicked on the Windows XP desktop and selected \"Properties\" from the context menu to open the display properties window. \n"
    },
    {
        "frame": 117,
        "event": "mousedown",
        "description": "The user navigated to the \"Appearance\" tab within the \"Display Properties\" window by clicking on the tab. \n"
    },
    {
        "frame": 215,
        "event": "mousedown",
        "description": "The user deactivated the screensaver by opening the \"Display Properties\" window, selecting \"None\" from the \"Screen saver\" dropdown menu, and likely clicking \"Apply\". \n"
    },
    {
        "frame": 338,
        "event": "mousedown",
        "description": "The user selected the \"Home/Office Desk\" power scheme within the \"Power Options Properties\" dialog box, likely to apply it or modify its specific settings. \n"
    },
    {
        "frame": 374,
        "event": "mousedown",
        "description": "The user selected the \"Presentation\" power scheme from the \"Power schemes\" dropdown menu within the \"Power Options Properties\" window. \n"
    },
    {
        "frame": 395,
        "event": "mousedown",
        "description": "Under the \"Power Schemes\" tab in the \"Power Options Properties\" dialog box, the user is changing the \"Turn off monitor\" setting within the \"Settings for Always On power scheme\" section to \"After RO mins\" from the dropdown menu. \n"
    },
    {
        "frame": 437,
        "event": "mousedown",
        "description": "**Summary:**\n\nWithin the \"Power Options Properties\" dialog box, under the \"Advanced\" tab and using the \"Always On\" power scheme, the user is about to set the \"System hibernates\" option to \"Never.\" \n"
    },
    {
        "frame": 482,
        "event": "mousedown",
        "description": "The user sets the \"Always On\" power scheme in the \"Power Options Properties\" dialog box and configures all power-saving options (monitor, hard disks, standby, hibernation) to \"Never.\" They then apply these changes. \n"
    },
    {
        "frame": 516,
        "event": "mousedown",
        "description": "The user configured the \"Always On\" power scheme in the \"Power Options Properties\" dialog box, setting \"Turn off monitor,\" \"Turn off hard disks,\" \"System standby,\" and \"System hibernates\" to \"Never.\" They clicked \"OK\" to apply these settings, ensuring the computer remains powered on continuously. \n"
    },
    {
        "frame": 544,
        "event": "mousedown",
        "description": "The user applied changes made within the \"Screen Saver\" tab of the \"Display Properties\" dialog box. \n"
    }
]